softsampling/__init__.py
softsampling/categorical/__init__.py
softsampling/categorical/combination.py
softsampling/categorical/sampling.py
softsampling/categorical/stratification.py
softsampling/mixed/__init__.py
softsampling/mixed/combination.py
softsampling/mixed/sampling.py
softsampling/mixed/stratification.py
softsampling/numerical/__init__.py
softsampling/numerical/combination.py
softsampling/numerical/sampling.py
softsampling/numerical/stratification.py
softsampling/utils/__init__.py
softsampling/utils/preprocessing.py
softsampling-0.0.1.dist-info/METADATA
softsampling-0.0.1.dist-info/WHEEL
softsampling-0.0.1.dist-info/top_level.txt
softsampling-0.0.1.dist-info/RECORD
